django_super_deduper/__init__.py
django_super_deduper/merge.py
django_super_deduper/models.py
django_super_deduper-0.1.4.dist-info/LICENSE.md
django_super_deduper-0.1.4.dist-info/METADATA
django_super_deduper-0.1.4.dist-info/WHEEL
django_super_deduper-0.1.4.dist-info/top_level.txt
django_super_deduper-0.1.4.dist-info/RECORD
