Metadata-Version: 2.1
Name: django-super-deduper
Version: 0.1.4
Summary: Utilities for deduping Django model instances
Home-page: https://github.com/mighty-justice/django-super-deduper
Author: UNKNOWN
Author-email: UNKNOWN
License: UNKNOWN
Platform: UNKNOWN
Classifier: Framework :: Django :: 1.11
Classifier: License :: OSI Approved :: MIT License
Classifier: Programming Language :: Python :: 3.6
Requires-Dist: django (>=1.11)
